LICENSE.rst
MANIFEST.in
README.rst
setup.py
src/node/__init__.py
src/node.ext.template.egg-info/PKG-INFO
src/node.ext.template.egg-info/SOURCES.txt
src/node.ext.template.egg-info/dependency_links.txt
src/node.ext.template.egg-info/entry_points.txt
src/node.ext.template.egg-info/namespace_packages.txt
src/node.ext.template.egg-info/requires.txt
src/node.ext.template.egg-info/top_level.txt
src/node.ext.template.egg-info/zip-safe
src/node/ext/__init__.py
src/node/ext/template/__init__.py
src/node/ext/template/codesectionhandler.py
src/node/ext/template/codesectionhandler.rst
src/node/ext/template/interfaces.py
src/node/ext/template/template.py
src/node/ext/template/template.rst
src/node/ext/template/tests.py