Metadata-Version: 1.1
Name: node.ext.template
Version: 0.1
Summary: Template file abstraction based on nodes
Home-page: http://github.com/bluedynamics/node.ext.template
Author: BlueDynamics Alliance
Author-email: dev@bluedynamics.com
License: BSD
Platform: UNKNOWN
Classifier: License :: OSI Approved :: BSD License
Classifier: Intended Audience :: Developers
Classifier: Topic :: Software Development
Classifier: Operating System :: OS Independent
Classifier: Programming Language :: Python
